src/__init__.py
src/cmd.py
src/pkg/config.py
src/pkg/users.py
src/pkg/utils.py
dtaas_cli-0.1.5.dist-info/METADATA
dtaas_cli-0.1.5.dist-info/WHEEL
dtaas_cli-0.1.5.dist-info/entry_points.txt
dtaas_cli-0.1.5.dist-info/RECORD
